odoo/addons/l10n_es_facturae_custom_rounding/README.rst
odoo/addons/l10n_es_facturae_custom_rounding/__init__.py
odoo/addons/l10n_es_facturae_custom_rounding/__manifest__.py
odoo/addons/l10n_es_facturae_custom_rounding/models/__init__.py
odoo/addons/l10n_es_facturae_custom_rounding/models/account_move.py
odoo/addons/l10n_es_facturae_custom_rounding/readme/CONFIGURE.md
odoo/addons/l10n_es_facturae_custom_rounding/readme/CONTRIBUTORS.md
odoo/addons/l10n_es_facturae_custom_rounding/readme/DESCRIPTION.md
odoo/addons/l10n_es_facturae_custom_rounding/readme/USAGE.md
odoo/addons/l10n_es_facturae_custom_rounding/static/description/icon.png
odoo/addons/l10n_es_facturae_custom_rounding/static/description/index.html
odoo/addons/l10n_es_facturae_custom_rounding/tests/__init__.py
odoo/addons/l10n_es_facturae_custom_rounding/tests/test_facturae_custom_rounding.py
odoo_addon_l10n_es_facturae_custom_rounding-15.0.1.0.0.2.dist-info/METADATA
odoo_addon_l10n_es_facturae_custom_rounding-15.0.1.0.0.2.dist-info/WHEEL
odoo_addon_l10n_es_facturae_custom_rounding-15.0.1.0.0.2.dist-info/top_level.txt
odoo_addon_l10n_es_facturae_custom_rounding-15.0.1.0.0.2.dist-info/RECORD
